Metadata-Version: 2.4
Name: llama-index-vector-stores-jaguar
Version: 0.4.1
Summary: llama-index vector_stores jaguar integration
Author-email: Your Name <you@example.com>
License-Expression: MIT
License-File: LICENSE
Requires-Python: <4.0,>=3.9
Requires-Dist: jaguardb-http-client<4,>=3.4.2
Requires-Dist: llama-index-core<0.15,>=0.13.0
